asyncapi_container/__init__.py
asyncapi_container/asyncapi/__init__.py
asyncapi_container/asyncapi/generators/__init__.py
asyncapi_container/asyncapi/generators/base.py
asyncapi_container/asyncapi/generators/v3/__init__.py
asyncapi_container/asyncapi/generators/v3/generator.py
asyncapi_container/asyncapi/spec/__init__.py
asyncapi_container/asyncapi/spec/v3/__init__.py
asyncapi_container/asyncapi/spec/v3/external_docs.py
asyncapi_container/asyncapi/spec/v3/info.py
asyncapi_container/asyncapi/spec/v3/root.py
asyncapi_container/asyncapi/spec/v3/tag.py
asyncapi_container/containers/__init__.py
asyncapi_container/containers/v3/__init__.py
asyncapi_container/containers/v3/simple_channels.py
asyncapi_container/containers/v3/simple_spec.py
asyncapi_container/custom_types.py
asyncapi_container/utils.py
asyncapi_container-0.4.4.dist-info/LICENSE
asyncapi_container-0.4.4.dist-info/METADATA
asyncapi_container-0.4.4.dist-info/WHEEL
asyncapi_container-0.4.4.dist-info/RECORD
