Metadata-Version: 2.3
Name: asyncapi-container
Version: 0.4.4
Summary: 
Author: Sergei Konik
Author-email: s.konik.dev@gmail.com
Requires-Python: >=3.10,<4.0
Classifier: Programming Language :: Python :: 3
Classifier: Programming Language :: Python :: 3.10
Classifier: Programming Language :: Python :: 3.11
Classifier: Programming Language :: Python :: 3.12
Classifier: Programming Language :: Python :: 3.13
Requires-Dist: attrs (>=23.2.0,<24.0.0)
Requires-Dist: pydantic (>=2.12.5,<3.0.0)
